passbolt/__init__.py
pypassbolt_api-0.0.4.dist-info/METADATA
pypassbolt_api-0.0.4.dist-info/WHEEL
pypassbolt_api-0.0.4.dist-info/top_level.txt
pypassbolt_api-0.0.4.dist-info/RECORD
