Metadata-Version: 2.1
Name: pypassbolt-api
Version: 0.0.4
Summary: Python library for Passbolt, an open-source manager for teams
Home-page: https://github.com/mjavint/pypassbolt_api
Author: Manuel Vinent Guilarte
Author-email: mjavint@gmail.com
License: MIT
Project-URL: Documentation, https://github.com/mjavint/pypassbolt_api/blob/main/README.md
Project-URL: Source, https://github.com/mjavint/pypassbolt_api
Project-URL: Tracker, https://github.com/mjavint/pypassbolt_api/issues
Classifier: Programming Language :: Python :: 3
Classifier: Operating System :: OS Independent
Requires-Python: >=3.6
Requires-Dist: httpx ==0.26.0
Requires-Dist: PGPy ==0.6.0
Requires-Dist: python-gnupg ==0.5.2
Provides-Extra: all
Requires-Dist: pytest >=6.2.2 ; extra == 'all'
Requires-Dist: pycodestyle ; extra == 'all'
Requires-Dist: pytest-cov ; extra == 'all'
Provides-Extra: test
Requires-Dist: pytest >=6.2.2 ; extra == 'test'
Requires-Dist: pycodestyle ; extra == 'test'
Requires-Dist: pytest-cov ; extra == 'test'
